calculator.py
test_calculator.py
python_getting_started-0.0.4.dist-info/METADATA
python_getting_started-0.0.4.dist-info/WHEEL
python_getting_started-0.0.4.dist-info/top_level.txt
python_getting_started-0.0.4.dist-info/RECORD
