Metadata-Version: 2.1
Name: python_getting_started
Version: 0.0.4
Summary: A small calculator exmaple package
Author-email: Varshini <varshini@cognitree.com>
Project-URL: Homepage, https://github.com/pypa/sampleproject
Project-URL: Issues, https://github.com/pypa/sampleproject/issues
Classifier: Programming Language :: Python :: 3
Classifier: License :: OSI Approved :: MIT License
Classifier: Operating System :: OS Independent
Requires-Python: >=3.10
